autotagical/__init__.py
autotagical/categories.py
autotagical/file_handler.py
autotagical/filtering.py
autotagical/groups.py
autotagical/moving.py
autotagical/naming.py
autotagical/schema.py
autotagical/settings.py
autotagical/json_schema/category_file_schema.json
autotagical/json_schema/schema_file_schema.json
autotagical/json_schema/tag_group_file_schema.json
autotagical/json_schema/tagspaces_category_schema.json
autotagical/json_schema/tagspaces_tag_group_schema.json
autotagical-1.1.0.data/scripts/autotagical
autotagical-1.1.0.dist-info/LICENSE.md
autotagical-1.1.0.dist-info/METADATA
autotagical-1.1.0.dist-info/WHEEL
autotagical-1.1.0.dist-info/top_level.txt
autotagical-1.1.0.dist-info/RECORD
