Metadata-Version: 2.1
Name: autotagical
Version: 1.1.0
Summary: A utility to automagically rename and sort tagged files (such as those produced by TagSpaces) according to user-defined schemas.
Home-page: https://github.com/SiriusStarr/autotagical
Author: SiriusStarr
Author-email: 2049163+SiriusStarr@users.noreply.github.com
License: GPLv3
Keywords: file sort tag rename tagging tagspaces
Platform: UNKNOWN
Classifier: Development Status :: 5 - Production/Stable
Classifier: Environment :: Console
Classifier: Topic :: Utilities
Classifier: License :: OSI Approved :: GNU General Public License v3 (GPLv3)
Requires-Dist: setuptools
Requires-Dist: jsonschema (>=3)
Requires-Dist: packaging
